icefile/__init__.py
tkmsg/__init__.py
tkmsg-1.1.0.dist-info/METADATA
tkmsg-1.1.0.dist-info/WHEEL
tkmsg-1.1.0.dist-info/top_level.txt
tkmsg-1.1.0.dist-info/RECORD
