Metadata-Version: 2.1
Name: tkmsg
Version: 1.1.0
Summary: This module has a more beautiful pop-up window
Author: ice
Author-email: bilibili_wulihb@outlook.com
Classifier: Programming Language :: Python :: 3
Classifier: License :: OSI Approved :: MIT License
Classifier: Operating System :: OS Independent
